{"author":{"banner_url":"/assets/images/profiles/default_bg.png","bio":"Goodbye. https://ruqqus.com/+The_Cabal/post/d9y9/i-told-you-so-all-the\r\n\r\nRemember: History repeats, and the unaware are doomed to repeat it.","bio_html":"<p>Goodbye. <a href=\"https://ruqqus.com/+The_Cabal/post/d9y9/i-told-you-so-all-the\" target=\"_blank\">https://ruqqus.com/+The_Cabal/post/d9y9/i-told-you-so-all-the</a></p>\n<p>Remember: History repeats, and the unaware are doomed to repeat it.</p>\n","created_utc":1590615852,"id":"3eb","is_banned":0,"is_premium":false,"is_private":true,"permalink":"/@CrystalVulpine","profile_url":"https://api.ruqqus.com/assets/images/profiles/default-profile-pic.png","title":null,"username":"CrystalVulpine"},"author_name":"CrystalVulpine","award_count":0,"body":"","body_html":"","comment_count":0,"created_utc":1601998639,"domain":"gfycat.com","downvotes":1,"edited_utc":0,"fullname":"t2_3tb9","guild":{"banner_url":"https://i.ruqqus.com/board/aww/banner-1.png","color":"#62CA56","created_utc":1585276481,"description":"Aww ","description_html":"<p>Aww</p>\n","disallowbots":false,"fullname":"t4_bi","id":"bi","is_banned":false,"is_private":false,"is_restricted":false,"is_siege_protected":false,"name":"Aww","over_18":false,"permalink":"/+Aww","profile_url":"https://i.ruqqus.com/board/aww/profile-2.png"},"guild_id":"bi","guild_name":"Aww","herald_guild":null,"id":"3tb9","is_archived":true,"is_banned":false,"is_bot":false,"is_crosspost":false,"is_deleted":false,"is_distinguished":false,"is_heralded":false,"is_nsfl":false,"is_nsfw":false,"is_offensive":false,"is_pinned":false,"meta_description":null,"meta_title":null,"original_guild":null,"original_guild_id":null,"original_guild_name":null,"permalink":"/+Aww/post/3tb9/trying-to-play-and-sleep-at","score":13,"thumb_url":"https://i.ruqqus.com/posts/3tb9/thumb.png","title":"Trying to play and sleep at the same time","upvotes":15,"url":"https://gfycat.com/maturefancyeasternnewt","voted":0}
